think.py
think-0.1.2.dist-info/WHEEL
think-0.1.2.dist-info/top_level.txt
think-0.1.2.dist-info/RECORD
think-0.1.2.dist-info/metadata.json
think-0.1.2.dist-info/DESCRIPTION.rst
think-0.1.2.dist-info/entry_points.txt
think-0.1.2.dist-info/METADATA
