Metadata-Version: 1.1
Name: think
Version: 0.1.2
Summary: Terminal Think Music
Home-page: https://github.com/Kwpolska/think
Author: Chris Warrick
Author-email: chris@chriswarrick.com
License: 3-clause BSD
Keywords: think music,Jeopardy!,game show
Platform: POSIX
Classifier: Development Status :: 5 - Production/Stable
Classifier: Environment :: Console
Classifier: Intended Audience :: System Administrators
Classifier: License :: OSI Approved :: BSD License
Classifier: Operating System :: POSIX
Classifier: Topic :: Multimedia :: Sound/Audio :: Players
Classifier: Programming Language :: Python
Classifier: Programming Language :: Python :: 2
Classifier: Programming Language :: Python :: 2.7
Classifier: Programming Language :: Python :: 3
Classifier: Programming Language :: Python :: 3.3
Classifier: Programming Language :: Python :: 3.4
